dsl/__init__.py
dsl/dsl.py
dsl/plot.py
dsl/power_dsl.py
dsl_kit-0.1.1.dist-info/METADATA
dsl_kit-0.1.1.dist-info/WHEEL
dsl_kit-0.1.1.dist-info/top_level.txt
dsl_kit-0.1.1.dist-info/RECORD
