Metadata-Version: 2.4
Name: dsl_kit
Version: 0.1.1
Summary: Design-based Supervised Learning (DSL) framework in Python
Author-email: Enan Srivastava <contact@enan.dev>
License-Expression: MIT
Project-URL: Homepage, https://github.com/Enan456/dsl-python/
Project-URL: Bug Tracker, https://github.com/Enan456/dsl-python/issues
Classifier: Programming Language :: Python :: 3
Classifier: Operating System :: OS Independent
Classifier: Development Status :: 3 - Alpha
Classifier: Intended Audience :: Science/Research
Classifier: Topic :: Scientific/Engineering
Requires-Python: >=3.9
Requires-Dist: numpy>=1.20.0
Requires-Dist: pandas>=1.3.0
Requires-Dist: scipy>=1.7.0
Requires-Dist: scikit-learn>=1.0.0
Requires-Dist: matplotlib>=3.4.0
Requires-Dist: patsy>=0.5.0
Requires-Dist: statsmodels>=0.14.0
Requires-Dist: pyarrow>=14.0.1
